[{"obj_id": "ZTF23aasxbqp", "ra": null, "dec": null, "filter": "ztfi", "mjd": 60116.428101900034, "snr": null, "instrument_id": 1, "instrument_name": "ZTF", "ra_unc": null, "dec_unc": null, "origin": "None", "id": 468284604, "altdata": null, "created_at": "2023-07-19T12:21:39.883802", "groups": [{"id": 3, "created_at": "2020-10-21T06:20:33.630657", "modified": "2020-10-21T06:20:33.630657", "nickname": null, "name": "kowalski-bot", "description": null, "private": false, "single_user_group": true}], "annotations": [], "mag": null, "magerr": null, "magsys": "ab", "limiting_mag": 19.30739974975586}, {"obj_id": "ZTF23aasxbqp", "ra": null, "dec": null, "filter": "ztfi", "mjd": 60120.4584144, "snr": null, "instrument_id": 1, "instrument_name": "ZTF", "ra_unc": null, "dec_unc": null, "origin": "None", "id": 468284605, "altdata": null, "created_at": "2023-07-19T12:21:39.883881", "groups": [{"id": 3, "created_at": "2020-10-21T06:20:33.630657", "modified": "2020-10-21T06:20:33.630657", "nickname": null, "name": "kowalski-bot", "description": null, "private": false, "single_user_group": true}], "annotations": [], "mag": null, "magerr": null, "magsys": "ab", "limiting_mag": 19.667499542236328}, {"obj_id": "ZTF23aasxbqp", "ra": null, "dec": null, "filter": "ztfg", "mjd": 60124.41175930016, "snr": null, "instrument_id": 1, "instrument_name": "ZTF", "ra_unc": null, "dec_unc": null, "origin": "None", "id": 468205788, "altdata": null, "created_at": "2023-07-19T10:20:59.326893", "groups": [{"id": 3, "created_at": "2020-10-21T06:20:33.630657", "modified": "2020-10-21T06:20:33.630657", "nickname": null, "name": "kowalski-bot", "description": null, "private": false, "single_user_group": true}], "annotations": [], "mag": null, "magerr": null, "magsys": "ab", "limiting_mag": 20.318700790405273}, {"obj_id": "ZTF23aasxbqp", "ra": null, "dec": null, "filter": "ztfr", "mjd": 60124.4490278, "snr": null, "instrument_id": 1, "instrument_name": "ZTF", "ra_unc": null, "dec_unc": null, "origin": "None", "id": 468205789, "altdata": null, "created_at": "2023-07-19T10:20:59.326948", "groups": [{"id": 3, "created_at": "2020-10-21T06:20:33.630657", "modified": "2020-10-21T06:20:33.630657", "nickname": null, "name": "kowalski-bot", "description": null, "private": false, "single_user_group": true}], "annotations": [], "mag": null, "magerr": null, "magsys": "ab", "limiting_mag": 20.44969940185547}, {"obj_id": "ZTF23aasxbqp", "ra": null, "dec": null, "filter": "ztfg", "mjd": 60126.42302080011, "snr": null, "instrument_id": 1, "instrument_name": "ZTF", "ra_unc": null, "dec_unc": null, "origin": "None", "id": 468205790, "altdata": null, "created_at": "2023-07-19T10:20:59.326966", "groups": [{"id": 3, "created_at": "2020-10-21T06:20:33.630657", "modified": "2020-10-21T06:20:33.630657", "nickname": null, "name": "kowalski-bot", "description": null, "private": false, "single_user_group": true}], "annotations": [], "mag": null, "magerr": null, "magsys": "ab", "limiting_mag": 19.927000045776367}, {"obj_id": "ZTF23aasxbqp", "ra": null, "dec": null, "filter": "ztfr", "mjd": 60126.45396990003, "snr": null, "instrument_id": 1, "instrument_name": "ZTF", "ra_unc": null, "dec_unc": null, "origin": "None", "id": 468205791, "altdata": null, "created_at": "2023-07-19T10:20:59.326982", "groups": [{"id": 3, "created_at": "2020-10-21T06:20:33.630657", "modified": "2020-10-21T06:20:33.630657", "nickname": null, "name": "kowalski-bot", "description": null, "private": false, "single_user_group": true}], "annotations": [], "mag": null, "magerr": null, "magsys": "ab", "limiting_mag": 20.61440086364746}, {"obj_id": "ZTF23aasxbqp", "ra": null, "dec": null, "filter": "ztfr", "mjd": 60133.40827549994, "snr": null, "instrument_id": 1, "instrument_name": "ZTF", "ra_unc": null, "dec_unc": null, "origin": "None", "id": 468205792, "altdata": null, "created_at": "2023-07-19T10:20:59.326997", "groups": [{"id": 3, "created_at": "2020-10-21T06:20:33.630657", "modified": "2020-10-21T06:20:33.630657", "nickname": null, "name": "kowalski-bot", "description": null, "private": false, "single_user_group": true}], "annotations": [], "mag": null, "magerr": null, "magsys": "ab", "limiting_mag": 20.165800094604492}, {"obj_id": "ZTF23aasxbqp", "ra": null, "dec": null, "filter": "ztfi", "mjd": 60133.43490740005, "snr": null, "instrument_id": 1, "instrument_name": "ZTF", "ra_unc": null, "dec_unc": null, "origin": "None", "id": 468284606, "altdata": null, "created_at": "2023-07-19T12:21:39.883909", "groups": [{"id": 3, "created_at": "2020-10-21T06:20:33.630657", "modified": "2020-10-21T06:20:33.630657", "nickname": null, "name": "kowalski-bot", "description": null, "private": false, "single_user_group": true}], "annotations": [], "mag": null, "magerr": null, "magsys": "ab", "limiting_mag": 19.89349937438965}, {"obj_id": "ZTF23aasxbqp", "ra": null, "dec": null, "filter": "ztfg", "mjd": 60133.45403939998, "snr": null, "instrument_id": 1, "instrument_name": "ZTF", "ra_unc": null, "dec_unc": null, "origin": "None", "id": 468205793, "altdata": null, "created_at": "2023-07-19T10:20:59.327011", "groups": [{"id": 3, "created_at": "2020-10-21T06:20:33.630657", "modified": "2020-10-21T06:20:33.630657", "nickname": null, "name": "kowalski-bot", "description": null, "private": false, "single_user_group": true}], "annotations": [], "mag": null, "magerr": null, "magsys": "ab", "limiting_mag": 20.03700065612793}, {"obj_id": "ZTF23aasxbqp", "ra": null, "dec": null, "filter": "ztfg", "mjd": 60135.40534720011, "snr": null, "instrument_id": 1, "instrument_name": "ZTF", "ra_unc": null, "dec_unc": null, "origin": "None", "id": 468205794, "altdata": null, "created_at": "2023-07-19T10:20:59.327027", "groups": [{"id": 3, "created_at": "2020-10-21T06:20:33.630657", "modified": "2020-10-21T06:20:33.630657", "nickname": null, "name": "kowalski-bot", "description": null, "private": false, "single_user_group": true}], "annotations": [], "mag": null, "magerr": null, "magsys": "ab", "limiting_mag": 20.05699920654297}, {"obj_id": "ZTF23aasxbqp", "ra": null, "dec": null, "filter": "ztfr", "mjd": 60135.46249999991, "snr": null, "instrument_id": 1, "instrument_name": "ZTF", "ra_unc": null, "dec_unc": null, "origin": "None", "id": 468205795, "altdata": null, "created_at": "2023-07-19T10:20:59.327040", "groups": [{"id": 3, "created_at": "2020-10-21T06:20:33.630657", "modified": "2020-10-21T06:20:33.630657", "nickname": null, "name": "kowalski-bot", "description": null, "private": false, "single_user_group": true}], "annotations": [], "mag": null, "magerr": null, "magsys": "ab", "limiting_mag": 20.39579963684082}, {"obj_id": "ZTF23aasxbqp", "ra": null, "dec": null, "filter": "ztfi", "mjd": 60137.44957179995, "snr": null, "instrument_id": 1, "instrument_name": "ZTF", "ra_unc": null, "dec_unc": null, "origin": "None", "id": 468284607, "altdata": null, "created_at": "2023-07-19T12:21:39.883934", "groups": [{"id": 3, "created_at": "2020-10-21T06:20:33.630657", "modified": "2020-10-21T06:20:33.630657", "nickname": null, "name": "kowalski-bot", "description": null, "private": false, "single_user_group": true}], "annotations": [], "mag": null, "magerr": null, "magsys": "ab", "limiting_mag": 19.953100204467773}, {"obj_id": "ZTF23aasxbqp", "ra": null, "dec": null, "filter": "ztfg", "mjd": 60138.42504630005, "snr": null, "instrument_id": 1, "instrument_name": "ZTF", "ra_unc": null, "dec_unc": null, "origin": "None", "id": 468205796, "altdata": null, "created_at": "2023-07-19T10:20:59.327053", "groups": [{"id": 3, "created_at": "2020-10-21T06:20:33.630657", "modified": "2020-10-21T06:20:33.630657", "nickname": null, "name": "kowalski-bot", "description": null, "private": false, "single_user_group": true}], "annotations": [], "mag": null, "magerr": null, "magsys": "ab", "limiting_mag": 20.3262996673584}, {"obj_id": "ZTF23aasxbqp", "ra": null, "dec": null, "filter": "ztfr", "mjd": 60138.46030090004, "snr": null, "instrument_id": 1, "instrument_name": "ZTF", "ra_unc": null, "dec_unc": null, "origin": "None", "id": 468205797, "altdata": null, "created_at": "2023-07-19T10:20:59.327066", "groups": [{"id": 3, "created_at": "2020-10-21T06:20:33.630657", "modified": "2020-10-21T06:20:33.630657", "nickname": null, "name": "kowalski-bot", "description": null, "private": false, "single_user_group": true}], "annotations": [], "mag": null, "magerr": null, "magsys": "ab", "limiting_mag": 19.644500732421875}, {"obj_id": "ZTF23aasxbqp", "ra": null, "dec": null, "filter": "ztfg", "mjd": 60141.340752299875, "snr": null, "instrument_id": 1, "instrument_name": "ZTF", "ra_unc": null, "dec_unc": null, "origin": "None", "id": 468205798, "altdata": null, "created_at": "2023-07-19T10:20:59.327079", "groups": [{"id": 3, "created_at": "2020-10-21T06:20:33.630657", "modified": "2020-10-21T06:20:33.630657", "nickname": null, "name": "kowalski-bot", "description": null, "private": false, "single_user_group": true}], "annotations": [], "mag": null, "magerr": null, "magsys": "ab", "limiting_mag": 20.327499389648438}, {"obj_id": "ZTF23aasxbqp", "ra": null, "dec": null, "filter": "ztfr", "mjd": 60141.42952550016, "snr": null, "instrument_id": 1, "instrument_name": "ZTF", "ra_unc": null, "dec_unc": null, "origin": "None", "id": 468205799, "altdata": null, "created_at": "2023-07-19T10:20:59.327091", "groups": [{"id": 3, "created_at": "2020-10-21T06:20:33.630657", "modified": "2020-10-21T06:20:33.630657", "nickname": null, "name": "kowalski-bot", "description": null, "private": false, "single_user_group": true}], "annotations": [], "mag": null, "magerr": null, "magsys": "ab", "limiting_mag": 20.54560089111328}, {"obj_id": "ZTF23aasxbqp", "ra": null, "dec": null, "filter": "ztfi", "mjd": 60141.45136569999, "snr": null, "instrument_id": 1, "instrument_name": "ZTF", "ra_unc": null, "dec_unc": null, "origin": "None", "id": 468284608, "altdata": null, "created_at": "2023-07-19T12:21:39.883958", "groups": [{"id": 3, "created_at": "2020-10-21T06:20:33.630657", "modified": "2020-10-21T06:20:33.630657", "nickname": null, "name": "kowalski-bot", "description": null, "private": false, "single_user_group": true}], "annotations": [], "mag": null, "magerr": null, "magsys": "ab", "limiting_mag": 19.826200485229492}, {"obj_id": "ZTF23aasxbqp", "ra": 12.1353321, "dec": 41.6271833, "filter": "ztfr", "mjd": 60144.38751159981, "snr": 15.354977419837658, "instrument_id": 1, "instrument_name": "ZTF", "ra_unc": null, "dec_unc": null, "origin": "None", "id": 468205800, "altdata": null, "created_at": "2023-07-19T10:20:59.327104", "groups": [{"id": 3, "created_at": "2020-10-21T06:20:33.630657", "modified": "2020-10-21T06:20:33.630657", "nickname": null, "name": "kowalski-bot", "description": null, "private": false, "single_user_group": true}], "annotations": [], "mag": 18.65178717936527, "magerr": 0.07070907205343245, "magsys": "ab", "limiting_mag": 19.86998512385179}, {"obj_id": "ZTF23aasxbqp", "ra": 12.1353321, "dec": 41.6271833, "filter": "ztfr", "mjd": 60144.38751159981, "snr": 15.354993599319872, "instrument_id": 1, "instrument_name": "ZTF", "ra_unc": null, "dec_unc": null, "origin": "None", "id": 468260634, "altdata": null, "created_at": "2023-07-19T11:56:38.369014", "groups": [{"id": 3, "created_at": "2020-10-21T06:20:33.630657", "modified": "2020-10-21T06:20:33.630657", "nickname": null, "name": "kowalski-bot", "description": null, "private": false, "single_user_group": true}], "annotations": [], "mag": 18.65180029486869, "magerr": 0.0707089975476265, "magsys": "ab", "limiting_mag": 19.869999383390777}, {"obj_id": "ZTF23aasxbqp", "ra": 12.1352841, "dec": 41.6271649, "filter": "ztfg", "mjd": 60144.44472219981, "snr": 14.366492038464715, "instrument_id": 1, "instrument_name": "ZTF", "ra_unc": null, "dec_unc": null, "origin": "None", "id": 468260635, "altdata": null, "created_at": "2023-07-19T11:56:38.369083", "groups": [{"id": 3, "created_at": "2020-10-21T06:20:33.630657", "modified": "2020-10-21T06:20:33.630657", "nickname": null, "name": "kowalski-bot", "description": null, "private": false, "single_user_group": true}], "annotations": [], "mag": 19.288328381671228, "magerr": 0.07557420432567596, "magsys": "ab", "limiting_mag": 20.434280212126644}, {"obj_id": "ZTF23aasxbqp", "ra": 12.1352841, "dec": 41.6271649, "filter": "ztfg", "mjd": 60144.44472219981, "snr": 14.366530279724454, "instrument_id": 1, "instrument_name": "ZTF", "ra_unc": null, "dec_unc": null, "origin": "None", "id": 468284591, "altdata": null, "created_at": "2023-07-19T12:21:39.543965", "groups": [{"id": 3, "created_at": "2020-10-21T06:20:33.630657", "modified": "2020-10-21T06:20:33.630657", "nickname": null, "name": "kowalski-bot", "description": null, "private": false, "single_user_group": true}], "annotations": [], "mag": 19.288299834894417, "magerr": 0.07557400315999985, "magsys": "ab", "limiting_mag": 20.434254555398766}, {"obj_id": "ZTF23aasxbqp", "ra": 12.1353181, "dec": 41.6271762, "filter": "ztfi", "mjd": 60144.46609950019, "snr": 10.809471460963035, "instrument_id": 1, "instrument_name": "ZTF", "ra_unc": null, "dec_unc": null, "origin": "None", "id": 468284609, "altdata": null, "created_at": "2023-07-19T12:21:39.883983", "groups": [{"id": 3, "created_at": "2020-10-21T06:20:33.630657", "modified": "2020-10-21T06:20:33.630657", "nickname": null, "name": "kowalski-bot", "description": null, "private": false, "single_user_group": true}], "annotations": [], "mag": 18.953863526610913, "magerr": 0.1004430428147316, "magsys": "ab", "limiting_mag": 19.790949663882877}, {"obj_id": "ZTF23aasxbqp", "ra": null, "dec": null, "filter": "sdssg", "mjd": 60145.32746150019, "snr": 22.0844328989066, "instrument_id": 2, "instrument_name": "SEDM", "ra_unc": null, "dec_unc": null, "origin": "SEDM_FPIPE_SDSS", "id": 468543394, "altdata": null, "created_at": "2023-07-20T08:02:34.174028", "groups": [{"id": 1, "created_at": "2020-10-21T01:38:02.775252", "modified": "2020-10-21T01:38:02.775252", "nickname": null, "name": "Sitewide Group", "description": null, "private": false, "single_user_group": false}, {"id": 13, "created_at": "2020-10-21T06:20:33.841974", "modified": "2020-10-21T06:20:33.841974", "nickname": null, "name": "fremling", "description": null, "private": false, "single_user_group": true}], "annotations": [], "mag": 19.531800955814035, "magerr": 0.04916296514056669, "magsys": "ab", "limiting_mag": 21.144591573946688}, {"obj_id": "ZTF23aasxbqp", "ra": null, "dec": null, "filter": "sdssr", "mjd": 60145.33018090017, "snr": 35.605289078157334, "instrument_id": 2, "instrument_name": "SEDM", "ra_unc": null, "dec_unc": null, "origin": "SEDM_FPIPE_SDSS", "id": 468544995, "altdata": null, "created_at": "2023-07-20T08:05:27.805936", "groups": [{"id": 1, "created_at": "2020-10-21T01:38:02.775252", "modified": "2020-10-21T01:38:02.775252", "nickname": null, "name": "Sitewide Group", "description": null, "private": false, "single_user_group": false}, {"id": 13, "created_at": "2020-10-21T06:20:33.841974", "modified": "2020-10-21T06:20:33.841974", "nickname": null, "name": "fremling", "description": null, "private": false, "single_user_group": true}], "annotations": [], "mag": 18.942565361463473, "magerr": 0.03049367756500515, "magsys": "ab", "limiting_mag": 21.073926640979874}, {"obj_id": "ZTF23aasxbqp", "ra": null, "dec": null, "filter": "sdssi", "mjd": 60145.332901199814, "snr": 13.901396464110727, "instrument_id": 2, "instrument_name": "SEDM", "ra_unc": null, "dec_unc": null, "origin": "SEDM_FPIPE_SDSS", "id": 468548832, "altdata": null, "created_at": "2023-07-20T08:08:16.728933", "groups": [{"id": 1, "created_at": "2020-10-21T01:38:02.775252", "modified": "2020-10-21T01:38:02.775252", "nickname": null, "name": "Sitewide Group", "description": null, "private": false, "single_user_group": false}, {"id": 13, "created_at": "2020-10-21T06:20:33.841974", "modified": "2020-10-21T06:20:33.841974", "nickname": null, "name": "fremling", "description": null, "private": false, "single_user_group": true}], "annotations": [], "mag": 19.60111826339237, "magerr": 0.07810267173957505, "magsys": "ab", "limiting_mag": 20.71133932624415}, {"obj_id": "ZTF23aasxbqp", "ra": null, "dec": null, "filter": "sdssg", "mjd": 60146.067069, "snr": 4.68495500923852, "instrument_id": 33, "instrument_name": "IOO", "ra_unc": null, "dec_unc": null, "origin": "LT_IOO_PIPE", "id": 468790740, "altdata": null, "created_at": "2023-07-21T01:47:43.284383", "groups": [{"id": 1, "created_at": "2020-10-21T01:38:02.775252", "modified": "2020-10-21T01:38:02.775252", "nickname": null, "name": "Sitewide Group", "description": null, "private": false, "single_user_group": false}, {"id": 359, "created_at": "2021-10-25T15:55:20.890275", "modified": "2022-08-02T18:15:17.990364", "nickname": null, "name": "khinds", "description": null, "private": false, "single_user_group": true}], "annotations": [], "mag": 19.984168162350173, "magerr": 0.23174954777945714, "magsys": "ab", "limiting_mag": 20.80027233622137}, {"obj_id": "ZTF23aasxbqp", "ra": null, "dec": null, "filter": "sdssr", "mjd": 60146.068128, "snr": 9.173429061010962, "instrument_id": 33, "instrument_name": "IOO", "ra_unc": null, "dec_unc": null, "origin": "LT_IOO_PIPE", "id": 468790741, "altdata": null, "created_at": "2023-07-21T01:54:06.143505", "groups": [{"id": 1, "created_at": "2020-10-21T01:38:02.775252", "modified": "2020-10-21T01:38:02.775252", "nickname": null, "name": "Sitewide Group", "description": null, "private": false, "single_user_group": false}, {"id": 359, "created_at": "2021-10-25T15:55:20.890275", "modified": "2022-08-02T18:15:17.990364", "nickname": null, "name": "khinds", "description": null, "private": false, "single_user_group": true}], "annotations": [], "mag": 19.285192810297193, "magerr": 0.11835663605583878, "magsys": "ab", "limiting_mag": 21.299810540168796}, {"obj_id": "ZTF23aasxbqp", "ra": null, "dec": null, "filter": "sdssi", "mjd": 60146.069163, "snr": 5.324168392268693, "instrument_id": 33, "instrument_name": "IOO", "ra_unc": null, "dec_unc": null, "origin": "LT_IOO_PIPE", "id": 468790742, "altdata": null, "created_at": "2023-07-21T02:04:08.944088", "groups": [{"id": 1, "created_at": "2020-10-21T01:38:02.775252", "modified": "2020-10-21T01:38:02.775252", "nickname": null, "name": "Sitewide Group", "description": null, "private": false, "single_user_group": false}, {"id": 359, "created_at": "2021-10-25T15:55:20.890275", "modified": "2022-08-02T18:15:17.990364", "nickname": null, "name": "khinds", "description": null, "private": false, "single_user_group": true}], "annotations": [], "mag": 19.92558834702968, "magerr": 0.20392597017305905, "magsys": "ab", "limiting_mag": 20.96723162960993}, {"obj_id": "ZTF23aasxbqp", "ra": 12.1353467, "dec": 41.6271855, "filter": "ztfr", "mjd": 60146.40510419989, "snr": 10.546685932348733, "instrument_id": 1, "instrument_name": "ZTF", "ra_unc": null, "dec_unc": null, "origin": "None", "id": 469244493, "altdata": null, "created_at": "2023-07-21T11:38:26.418849", "groups": [{"id": 3, "created_at": "2020-10-21T06:20:33.630657", "modified": "2020-10-21T06:20:33.630657", "nickname": null, "name": "kowalski-bot", "description": null, "private": false, "single_user_group": true}], "annotations": [], "mag": 19.28028720642883, "magerr": 0.1029457226395607, "magsys": "ab", "limiting_mag": 20.0906522291751}, {"obj_id": "ZTF23aasxbqp", "ra": 12.1353467, "dec": 41.6271855, "filter": "ztfr", "mjd": 60146.40510419989, "snr": 10.546657690157781, "instrument_id": 1, "instrument_name": "ZTF", "ra_unc": null, "dec_unc": null, "origin": "None", "id": 469297073, "altdata": null, "created_at": "2023-07-21T12:27:52.376894", "groups": [{"id": 3, "created_at": "2020-10-21T06:20:33.630657", "modified": "2020-10-21T06:20:33.630657", "nickname": null, "name": "kowalski-bot", "description": null, "private": false, "single_user_group": true}], "annotations": [], "mag": 19.28030061050257, "magerr": 0.10294599831104279, "magsys": "ab", "limiting_mag": 20.09066272583219}, {"obj_id": "ZTF23aasxbqp", "ra": 12.1353096, "dec": 41.6271653, "filter": "ztfr", "mjd": 60146.45304400008, "snr": 14.204370003614224, "instrument_id": 1, "instrument_name": "ZTF", "ra_unc": null, "dec_unc": null, "origin": "None", "id": 469297074, "altdata": null, "created_at": "2023-07-21T12:27:52.376948", "groups": [{"id": 3, "created_at": "2020-10-21T06:20:33.630657", "modified": "2020-10-21T06:20:33.630657", "nickname": null, "name": "kowalski-bot", "description": null, "private": false, "single_user_group": true}], "annotations": [], "mag": 19.240762998481404, "magerr": 0.07643677294254302, "magsys": "ab", "limiting_mag": 20.37439292896591}, {"obj_id": "ZTF23aasxbqp", "ra": 12.1353096, "dec": 41.6271653, "filter": "ztfr", "mjd": 60146.45304400008, "snr": 14.204328467129885, "instrument_id": 1, "instrument_name": "ZTF", "ra_unc": null, "dec_unc": null, "origin": "None", "id": 470114742, "altdata": null, "created_at": "2023-07-23T13:42:55.140322", "groups": [{"id": 3, "created_at": "2020-10-21T06:20:33.630657", "modified": "2020-10-21T06:20:33.630657", "nickname": null, "name": "kowalski-bot", "description": null, "private": false, "single_user_group": true}], "annotations": [], "mag": 19.240801206730424, "magerr": 0.07643699645996094, "magsys": "ab", "limiting_mag": 20.374427962295464}, {"obj_id": "ZTF23aasxbqp", "ra": 12.1353308, "dec": 41.6272034, "filter": "ztfg", "mjd": 60148.452372699976, "snr": 5.445181883775584, "instrument_id": 1, "instrument_name": "ZTF", "ra_unc": null, "dec_unc": null, "origin": "None", "id": 470114743, "altdata": null, "created_at": "2023-07-23T13:42:55.140380", "groups": [{"id": 3, "created_at": "2020-10-21T06:20:33.630657", "modified": "2020-10-21T06:20:33.630657", "nickname": null, "name": "kowalski-bot", "description": null, "private": false, "single_user_group": true}], "annotations": [], "mag": 20.45994209688993, "magerr": 0.19939392805099487, "magsys": "ab", "limiting_mag": 20.552548063405542}, {"obj_id": "ZTF23aasxbqp", "ra": 12.1353308, "dec": 41.6272034, "filter": "ztfg", "mjd": 60148.452372699976, "snr": 5.445179849122286, "instrument_id": 1, "instrument_name": "ZTF", "ra_unc": null, "dec_unc": null, "origin": "None", "id": 471024438, "altdata": null, "created_at": "2023-07-25T12:43:26.286063", "groups": [{"id": 3, "created_at": "2020-10-21T06:20:33.630657", "modified": "2020-10-21T06:20:33.630657", "nickname": null, "name": "kowalski-bot", "description": null, "private": false, "single_user_group": true}], "annotations": [], "mag": 20.45990036592678, "magerr": 0.19939400255680084, "magsys": "ab", "limiting_mag": 20.552505926744807}, {"obj_id": "ZTF23aasxbqp", "ra": null, "dec": null, "filter": "ztfr", "mjd": 60148.46333329985, "snr": null, "instrument_id": 1, "instrument_name": "ZTF", "ra_unc": null, "dec_unc": null, "origin": "None", "id": 471024439, "altdata": null, "created_at": "2023-07-25T12:43:26.286126", "groups": [{"id": 3, "created_at": "2020-10-21T06:20:33.630657", "modified": "2020-10-21T06:20:33.630657", "nickname": null, "name": "kowalski-bot", "description": null, "private": false, "single_user_group": true}], "annotations": [], "mag": null, "magerr": null, "magsys": "ab", "limiting_mag": 19.509599685668945}, {"obj_id": "ZTF23aasxbqp", "ra": 12.1354166, "dec": 41.6271372, "filter": "ztfr", "mjd": 60150.451481500175, "snr": 5.08968660987195, "instrument_id": 1, "instrument_name": "ZTF", "ra_unc": null, "dec_unc": null, "origin": "None", "id": 471024440, "altdata": null, "created_at": "2023-07-25T12:43:26.286145", "groups": [{"id": 3, "created_at": "2020-10-21T06:20:33.630657", "modified": "2020-10-21T06:20:33.630657", "nickname": null, "name": "kowalski-bot", "description": null, "private": false, "single_user_group": true}], "annotations": [], "mag": 20.701551868430638, "magerr": 0.21332083642482758, "magsys": "ab", "limiting_mag": 20.72085446284634}]