[{"obj_id": "ZTF19aaojovs", "ra": null, "dec": null, "filter": "ztfg", "mjd": 58547.37614580011, "snr": null, "instrument_id": 1, "instrument_name": "ZTF", "ra_unc": null, "dec_unc": null, "origin": "", "id": 2662238, "altdata": null, "created_at": "2020-11-16T21:17:24.474793", "groups": [{"id": 37, "created_at": "2020-10-21T06:20:34.313318", "modified": "2020-10-21T06:20:34.313318", "nickname": null, "name": "andytzanidakis", "description": null, "private": false, "single_user_group": true}, {"id": 43, "created_at": "2020-10-21T06:20:34.462803", "modified": "2020-10-21T06:20:34.462803", "nickname": "clu", "name": "Census of the Local Universe Caltech", "description": null, "private": false, "single_user_group": false}], "annotations": [], "mag": null, "magerr": null, "magsys": "ab", "limiting_mag": 20.52869987487793}, {"obj_id": "ZTF19aaojovs", "ra": null, "dec": null, "filter": "ztfg", "mjd": 58562.31421299977, "snr": null, "instrument_id": 1, "instrument_name": "ZTF", "ra_unc": null, "dec_unc": null, "origin": "", "id": 2662239, "altdata": null, "created_at": "2020-11-16T21:17:24.474793", "groups": [{"id": 37, "created_at": "2020-10-21T06:20:34.313318", "modified": "2020-10-21T06:20:34.313318", "nickname": null, "name": "andytzanidakis", "description": null, "private": false, "single_user_group": true}, {"id": 43, "created_at": "2020-10-21T06:20:34.462803", "modified": "2020-10-21T06:20:34.462803", "nickname": "clu", "name": "Census of the Local Universe Caltech", "description": null, "private": false, "single_user_group": false}], "annotations": [], "mag": null, "magerr": null, "magsys": "ab", "limiting_mag": 15.780099868774414}, {"obj_id": "ZTF19aaojovs", "ra": null, "dec": null, "filter": "ztfr", "mjd": 58562.39767359989, "snr": null, "instrument_id": 1, "instrument_name": "ZTF", "ra_unc": null, "dec_unc": null, "origin": "", "id": 2662240, "altdata": null, "created_at": "2020-11-16T21:17:24.474793", "groups": [{"id": 37, "created_at": "2020-10-21T06:20:34.313318", "modified": "2020-10-21T06:20:34.313318", "nickname": null, "name": "andytzanidakis", "description": null, "private": false, "single_user_group": true}, {"id": 43, "created_at": "2020-10-21T06:20:34.462803", "modified": "2020-10-21T06:20:34.462803", "nickname": "clu", "name": "Census of the Local Universe Caltech", "description": null, "private": false, "single_user_group": false}], "annotations": [], "mag": null, "magerr": null, "magsys": "ab", "limiting_mag": 17.175600051879883}, {"obj_id": "ZTF19aaojovs", "ra": null, "dec": null, "filter": "ztfg", "mjd": 58567.3102545999, "snr": null, "instrument_id": 1, "instrument_name": "ZTF", "ra_unc": null, "dec_unc": null, "origin": "", "id": 2662241, "altdata": null, "created_at": "2020-11-16T21:17:24.474793", "groups": [{"id": 37, "created_at": "2020-10-21T06:20:34.313318", "modified": "2020-10-21T06:20:34.313318", "nickname": null, "name": "andytzanidakis", "description": null, "private": false, "single_user_group": true}, {"id": 43, "created_at": "2020-10-21T06:20:34.462803", "modified": "2020-10-21T06:20:34.462803", "nickname": "clu", "name": "Census of the Local Universe Caltech", "description": null, "private": false, "single_user_group": false}], "annotations": [], "mag": null, "magerr": null, "magsys": "ab", "limiting_mag": 19.74090003967285}, {"obj_id": "ZTF19aaojovs", "ra": null, "dec": null, "filter": "ztfr", "mjd": 58567.36137730023, "snr": null, "instrument_id": 1, "instrument_name": "ZTF", "ra_unc": null, "dec_unc": null, "origin": "", "id": 2662242, "altdata": null, "created_at": "2020-11-16T21:17:24.474793", "groups": [{"id": 37, "created_at": "2020-10-21T06:20:34.313318", "modified": "2020-10-21T06:20:34.313318", "nickname": null, "name": "andytzanidakis", "description": null, "private": false, "single_user_group": true}, {"id": 43, "created_at": "2020-10-21T06:20:34.462803", "modified": "2020-10-21T06:20:34.462803", "nickname": "clu", "name": "Census of the Local Universe Caltech", "description": null, "private": false, "single_user_group": false}], "annotations": [], "mag": null, "magerr": null, "magsys": "ab", "limiting_mag": 19.909700393676758}, {"obj_id": "ZTF19aaojovs", "ra": null, "dec": null, "filter": "ztfg", "mjd": 58572.33459489979, "snr": null, "instrument_id": 1, "instrument_name": "ZTF", "ra_unc": null, "dec_unc": null, "origin": "", "id": 2662243, "altdata": null, "created_at": "2020-11-16T21:17:24.474793", "groups": [{"id": 37, "created_at": "2020-10-21T06:20:34.313318", "modified": "2020-10-21T06:20:34.313318", "nickname": null, "name": "andytzanidakis", "description": null, "private": false, "single_user_group": true}, {"id": 43, "created_at": "2020-10-21T06:20:34.462803", "modified": "2020-10-21T06:20:34.462803", "nickname": "clu", "name": "Census of the Local Universe Caltech", "description": null, "private": false, "single_user_group": false}], "annotations": [], "mag": null, "magerr": null, "magsys": "ab", "limiting_mag": 20.138999938964844}, {"obj_id": "ZTF19aaojovs", "ra": null, "dec": null, "filter": "ztfr", "mjd": 58572.357164400164, "snr": null, "instrument_id": 1, "instrument_name": "ZTF", "ra_unc": null, "dec_unc": null, "origin": "", "id": 2662244, "altdata": null, "created_at": "2020-11-16T21:17:24.474793", "groups": [{"id": 37, "created_at": "2020-10-21T06:20:34.313318", "modified": "2020-10-21T06:20:34.313318", "nickname": null, "name": "andytzanidakis", "description": null, "private": false, "single_user_group": true}, {"id": 43, "created_at": "2020-10-21T06:20:34.462803", "modified": "2020-10-21T06:20:34.462803", "nickname": "clu", "name": "Census of the Local Universe Caltech", "description": null, "private": false, "single_user_group": false}], "annotations": [], "mag": null, "magerr": null, "magsys": "ab", "limiting_mag": 20.146699905395508}, {"obj_id": "ZTF19aaojovs", "ra": 202.2074312, "dec": 10.3821783, "filter": "ztfg", "mjd": 58575.314722199924, "snr": 7.0714952622806395, "instrument_id": 1, "instrument_name": "ZTF", "ra_unc": null, "dec_unc": null, "origin": "", "id": 2662245, "altdata": null, "created_at": "2020-11-16T21:17:24.474793", "groups": [{"id": 37, "created_at": "2020-10-21T06:20:34.313318", "modified": "2020-10-21T06:20:34.313318", "nickname": null, "name": "andytzanidakis", "description": null, "private": false, "single_user_group": true}, {"id": 43, "created_at": "2020-10-21T06:20:34.462803", "modified": "2020-10-21T06:20:34.462803", "nickname": "clu", "name": "Census of the Local Universe Caltech", "description": null, "private": false, "single_user_group": false}], "annotations": [], "mag": 19.312599182128906, "magerr": 0.15353700518608093, "magsys": "ab", "limiting_mag": 20.23740005493164}, {"obj_id": "ZTF19aaojovs", "ra": null, "dec": null, "filter": "ztfr", "mjd": 58575.37496529985, "snr": null, "instrument_id": 1, "instrument_name": "ZTF", "ra_unc": null, "dec_unc": null, "origin": "", "id": 2662246, "altdata": null, "created_at": "2020-11-16T21:17:24.474793", "groups": [{"id": 37, "created_at": "2020-10-21T06:20:34.313318", "modified": "2020-10-21T06:20:34.313318", "nickname": null, "name": "andytzanidakis", "description": null, "private": false, "single_user_group": true}, {"id": 43, "created_at": "2020-10-21T06:20:34.462803", "modified": "2020-10-21T06:20:34.462803", "nickname": "clu", "name": "Census of the Local Universe Caltech", "description": null, "private": false, "single_user_group": false}], "annotations": [], "mag": null, "magerr": null, "magsys": "ab", "limiting_mag": 19.202499389648438}, {"obj_id": "ZTF19aaojovs", "ra": 202.2074235, "dec": 10.3820637, "filter": "ztfg", "mjd": 58580.29798609996, "snr": 7.178705982562383, "instrument_id": 1, "instrument_name": "ZTF", "ra_unc": null, "dec_unc": null, "origin": "", "id": 2662247, "altdata": null, "created_at": "2020-11-16T21:17:24.474793", "groups": [{"id": 37, "created_at": "2020-10-21T06:20:34.313318", "modified": "2020-10-21T06:20:34.313318", "nickname": null, "name": "andytzanidakis", "description": null, "private": false, "single_user_group": true}, {"id": 43, "created_at": "2020-10-21T06:20:34.462803", "modified": "2020-10-21T06:20:34.462803", "nickname": "clu", "name": "Census of the Local Universe Caltech", "description": null, "private": false, "single_user_group": false}], "annotations": [], "mag": 20.033199310302734, "magerr": 0.15124399960041046, "magsys": "ab", "limiting_mag": 20.565000534057617}, {"obj_id": "ZTF19aaojovs", "ra": 202.2074292, "dec": 10.382146, "filter": "ztfr", "mjd": 58580.315555599984, "snr": 6.544561730746642, "instrument_id": 1, "instrument_name": "ZTF", "ra_unc": null, "dec_unc": null, "origin": "", "id": 2662248, "altdata": null, "created_at": "2020-11-16T21:17:24.474793", "groups": [{"id": 37, "created_at": "2020-10-21T06:20:34.313318", "modified": "2020-10-21T06:20:34.313318", "nickname": null, "name": "andytzanidakis", "description": null, "private": false, "single_user_group": true}, {"id": 43, "created_at": "2020-10-21T06:20:34.462803", "modified": "2020-10-21T06:20:34.462803", "nickname": "clu", "name": "Census of the Local Universe Caltech", "description": null, "private": false, "single_user_group": false}], "annotations": [], "mag": 19.679500579833984, "magerr": 0.16589899361133573, "magsys": "ab", "limiting_mag": 20.324800491333008}, {"obj_id": "ZTF19aaojovs", "ra": 202.2074627, "dec": 10.3821608, "filter": "ztfr", "mjd": 58583.31482640002, "snr": 8.413625086213512, "instrument_id": 1, "instrument_name": "ZTF", "ra_unc": null, "dec_unc": null, "origin": "", "id": 2662249, "altdata": null, "created_at": "2020-11-16T21:17:24.474793", "groups": [{"id": 37, "created_at": "2020-10-21T06:20:34.313318", "modified": "2020-10-21T06:20:34.313318", "nickname": null, "name": "andytzanidakis", "description": null, "private": false, "single_user_group": true}, {"id": 43, "created_at": "2020-10-21T06:20:34.462803", "modified": "2020-10-21T06:20:34.462803", "nickname": "clu", "name": "Census of the Local Universe Caltech", "description": null, "private": false, "single_user_group": false}], "annotations": [], "mag": 19.28849983215332, "magerr": 0.12904499471187592, "magsys": "ab", "limiting_mag": 20.192899703979492}, {"obj_id": "ZTF19aaojovs", "ra": 202.207473, "dec": 10.3821375, "filter": "ztfr", "mjd": 58586.33247689996, "snr": 8.93286524725617, "instrument_id": 1, "instrument_name": "ZTF", "ra_unc": null, "dec_unc": null, "origin": "", "id": 2662250, "altdata": null, "created_at": "2020-11-16T21:17:24.474793", "groups": [{"id": 37, "created_at": "2020-10-21T06:20:34.313318", "modified": "2020-10-21T06:20:34.313318", "nickname": null, "name": "andytzanidakis", "description": null, "private": false, "single_user_group": true}, {"id": 43, "created_at": "2020-10-21T06:20:34.462803", "modified": "2020-10-21T06:20:34.462803", "nickname": "clu", "name": "Census of the Local Universe Caltech", "description": null, "private": false, "single_user_group": false}], "annotations": [], "mag": 19.128999710083008, "magerr": 0.12154400348663329, "magsys": "ab", "limiting_mag": 20.13759994506836}, {"obj_id": "ZTF19aaojovs", "ra": 202.2074448, "dec": 10.3820534, "filter": "ztfr", "mjd": 58589.27287039999, "snr": 5.026091055805369, "instrument_id": 1, "instrument_name": "ZTF", "ra_unc": null, "dec_unc": null, "origin": "", "id": 2662251, "altdata": null, "created_at": "2020-11-16T21:17:24.474793", "groups": [{"id": 37, "created_at": "2020-10-21T06:20:34.313318", "modified": "2020-10-21T06:20:34.313318", "nickname": null, "name": "andytzanidakis", "description": null, "private": false, "single_user_group": true}, {"id": 43, "created_at": "2020-10-21T06:20:34.462803", "modified": "2020-10-21T06:20:34.462803", "nickname": "clu", "name": "Census of the Local Universe Caltech", "description": null, "private": false, "single_user_group": false}], "annotations": [], "mag": 19.018699645996094, "magerr": 0.21602000296115872, "magsys": "ab", "limiting_mag": 18.451799392700195}, {"obj_id": "ZTF19aaojovs", "ra": null, "dec": null, "filter": "ztfr", "mjd": 58593.27833329979, "snr": null, "instrument_id": 1, "instrument_name": "ZTF", "ra_unc": null, "dec_unc": null, "origin": "", "id": 2662252, "altdata": null, "created_at": "2020-11-16T21:17:24.474793", "groups": [{"id": 37, "created_at": "2020-10-21T06:20:34.313318", "modified": "2020-10-21T06:20:34.313318", "nickname": null, "name": "andytzanidakis", "description": null, "private": false, "single_user_group": true}, {"id": 43, "created_at": "2020-10-21T06:20:34.462803", "modified": "2020-10-21T06:20:34.462803", "nickname": "clu", "name": "Census of the Local Universe Caltech", "description": null, "private": false, "single_user_group": false}], "annotations": [], "mag": null, "magerr": null, "magsys": "ab", "limiting_mag": 19.14620018005371}, {"obj_id": "ZTF19aaojovs", "ra": null, "dec": null, "filter": "ztfg", "mjd": 58596.23200230021, "snr": null, "instrument_id": 1, "instrument_name": "ZTF", "ra_unc": null, "dec_unc": null, "origin": "", "id": 2662253, "altdata": null, "created_at": "2020-11-16T21:17:24.474793", "groups": [{"id": 37, "created_at": "2020-10-21T06:20:34.313318", "modified": "2020-10-21T06:20:34.313318", "nickname": null, "name": "andytzanidakis", "description": null, "private": false, "single_user_group": true}, {"id": 43, "created_at": "2020-10-21T06:20:34.462803", "modified": "2020-10-21T06:20:34.462803", "nickname": "clu", "name": "Census of the Local Universe Caltech", "description": null, "private": false, "single_user_group": false}], "annotations": [], "mag": null, "magerr": null, "magsys": "ab", "limiting_mag": 20.138399124145508}, {"obj_id": "ZTF19aaojovs", "ra": 202.2074629, "dec": 10.3820971, "filter": "ztfr", "mjd": 58596.27400460001, "snr": 8.765833933861925, "instrument_id": 1, "instrument_name": "ZTF", "ra_unc": null, "dec_unc": null, "origin": "", "id": 2662254, "altdata": null, "created_at": "2020-11-16T21:17:24.474793", "groups": [{"id": 37, "created_at": "2020-10-21T06:20:34.313318", "modified": "2020-10-21T06:20:34.313318", "nickname": null, "name": "andytzanidakis", "description": null, "private": false, "single_user_group": true}, {"id": 43, "created_at": "2020-10-21T06:20:34.462803", "modified": "2020-10-21T06:20:34.462803", "nickname": "clu", "name": "Census of the Local Universe Caltech", "description": null, "private": false, "single_user_group": false}], "annotations": [], "mag": 19.35540008544922, "magerr": 0.12386000156402588, "magsys": "ab", "limiting_mag": 20.23710060119629}, {"obj_id": "ZTF19aaojovs", "ra": null, "dec": null, "filter": "ztfg", "mjd": 58600.2335994998, "snr": null, "instrument_id": 1, "instrument_name": "ZTF", "ra_unc": null, "dec_unc": null, "origin": "", "id": 2662255, "altdata": null, "created_at": "2020-11-16T21:17:24.474793", "groups": [{"id": 37, "created_at": "2020-10-21T06:20:34.313318", "modified": "2020-10-21T06:20:34.313318", "nickname": null, "name": "andytzanidakis", "description": null, "private": false, "single_user_group": true}, {"id": 43, "created_at": "2020-10-21T06:20:34.462803", "modified": "2020-10-21T06:20:34.462803", "nickname": "clu", "name": "Census of the Local Universe Caltech", "description": null, "private": false, "single_user_group": false}], "annotations": [], "mag": null, "magerr": null, "magsys": "ab", "limiting_mag": 20.57979965209961}, {"obj_id": "ZTF19aaojovs", "ra": null, "dec": null, "filter": "ztfr", "mjd": 58600.27659719996, "snr": null, "instrument_id": 1, "instrument_name": "ZTF", "ra_unc": null, "dec_unc": null, "origin": "", "id": 2662256, "altdata": null, "created_at": "2020-11-16T21:17:24.474793", "groups": [{"id": 37, "created_at": "2020-10-21T06:20:34.313318", "modified": "2020-10-21T06:20:34.313318", "nickname": null, "name": "andytzanidakis", "description": null, "private": false, "single_user_group": true}, {"id": 43, "created_at": "2020-10-21T06:20:34.462803", "modified": "2020-10-21T06:20:34.462803", "nickname": "clu", "name": "Census of the Local Universe Caltech", "description": null, "private": false, "single_user_group": false}], "annotations": [], "mag": null, "magerr": null, "magsys": "ab", "limiting_mag": 20.645700454711914}, {"obj_id": "ZTF19aaojovs", "ra": null, "dec": null, "filter": "ztfr", "mjd": 58606.210833299905, "snr": null, "instrument_id": 1, "instrument_name": "ZTF", "ra_unc": null, "dec_unc": null, "origin": "", "id": 2662257, "altdata": null, "created_at": "2020-11-16T21:17:24.474793", "groups": [{"id": 37, "created_at": "2020-10-21T06:20:34.313318", "modified": "2020-10-21T06:20:34.313318", "nickname": null, "name": "andytzanidakis", "description": null, "private": false, "single_user_group": true}, {"id": 43, "created_at": "2020-10-21T06:20:34.462803", "modified": "2020-10-21T06:20:34.462803", "nickname": "clu", "name": "Census of the Local Universe Caltech", "description": null, "private": false, "single_user_group": false}], "annotations": [], "mag": null, "magerr": null, "magsys": "ab", "limiting_mag": 20.645200729370117}, {"obj_id": "ZTF19aaojovs", "ra": null, "dec": null, "filter": "ztfg", "mjd": 58606.379791699816, "snr": null, "instrument_id": 1, "instrument_name": "ZTF", "ra_unc": null, "dec_unc": null, "origin": "", "id": 2662258, "altdata": null, "created_at": "2020-11-16T21:17:24.474793", "groups": [{"id": 37, "created_at": "2020-10-21T06:20:34.313318", "modified": "2020-10-21T06:20:34.313318", "nickname": null, "name": "andytzanidakis", "description": null, "private": false, "single_user_group": true}, {"id": 43, "created_at": "2020-10-21T06:20:34.462803", "modified": "2020-10-21T06:20:34.462803", "nickname": "clu", "name": "Census of the Local Universe Caltech", "description": null, "private": false, "single_user_group": false}], "annotations": [], "mag": null, "magerr": null, "magsys": "ab", "limiting_mag": 20.680999755859375}, {"obj_id": "ZTF19aaojovs", "ra": 202.2074346, "dec": 10.3821296, "filter": "ztfr", "mjd": 58612.24837959977, "snr": 5.363317847650499, "instrument_id": 1, "instrument_name": "ZTF", "ra_unc": null, "dec_unc": null, "origin": "", "id": 2662259, "altdata": null, "created_at": "2020-11-16T21:17:24.474793", "groups": [{"id": 37, "created_at": "2020-10-21T06:20:34.313318", "modified": "2020-10-21T06:20:34.313318", "nickname": null, "name": "andytzanidakis", "description": null, "private": false, "single_user_group": true}, {"id": 43, "created_at": "2020-10-21T06:20:34.462803", "modified": "2020-10-21T06:20:34.462803", "nickname": "clu", "name": "Census of the Local Universe Caltech", "description": null, "private": false, "single_user_group": false}], "annotations": [], "mag": 20.278568267822266, "magerr": 0.2024374157190323, "magsys": "ab", "limiting_mag": 20.77578353881836}]